[
  {
    "type": "drawer",
    "children": [
      {
        "type": "header",
        "props": {
          "title": "Menu"
        },
        "children": [
          {
            "type": "icon_button",
            "component_key": "icon/close"
          }
        ]
      },
      {
        "type": "list",
        "children": [
          {
            "type": "list_item",
            "children": [
              {
                "type": "text",
                "props": {
                  "text": "Home"
                }
              },
              {
                "type": "icon",
                "component_key": "icon/chevron-down"
              }
            ]
          },
          {
            "type": "list_item",
            "children": [
              {
                "type": "text",
                "props": {
                  "text": "Profile"
                }
              },
              {
                "type": "icon",
                "component_key": "icon/chevron-down"
              }
            ]
          },
          {
            "type": "list_item",
            "children": [
              {
                "type": "text",
                "props": {
                  "text": "Settings"
                }
              },
              {
                "type": "icon",
                "component_key": "icon/chevron-down"
              }
            ]
          },
          {
            "type": "list_item",
            "children": [
              {
                "type": "text",
                "props": {
                  "text": "Notifications"
                }
              },
              {
                "type": "icon",
                "component_key": "icon/chevron-down"
              }
            ]
          },
          {
            "type": "list_item",
            "children": [
              {
                "type": "text",
                "props": {
                  "text": "Help"
                }
              },
              {
                "type": "icon",
                "component_key": "icon/chevron-down"
              }
            ]
          },
          {
            "type": "list_item",
            "children": [
              {
                "type": "text",
                "props": {
                  "text": "Logout"
                }
              },
              {
                "type": "icon",
                "component_key": "icon/chevron-down"
              }
            ]
          }
        ]
      }
    ]
  }
]