{
  "returncode": 0,
  "latency_ms": 139,
  "timeout": false,
  "stdout": "[script.js] OK in 93ms: {\"type\":\"PROXY_EXECUTE_RESULT\",\"id\":\"run_1776452913890\",\"result\":{\"success\":true,\"result\":{\"__ok\":true,\"before\":1,\"after\":3,\"moved\":0,\"errors\":[{\"kind\":\"leaf_type_append_skipped\",\"parent_eid\":\"link-1\",\"parent_type\":\"link\",\"child_eid\":\"text-6\",\"child_type\":\"text\"}]}}}\n",
  "stderr": "",
  "parsed": {
    "__ok": true,
    "before": 1,
    "after": 3,
    "moved": 0,
    "errors": [
      {
        "kind": "leaf_type_append_skipped",
        "parent_eid": "link-1",
        "parent_type": "link",
        "child_eid": "text-6",
        "child_type": "text"
      }
    ]
  }
}